naja_atra_redis_session/__init__.py
naja_atra_redis_session/redis_session.py
naja_atra_redis_session-1.0.1.dist-info/LICENSE
naja_atra_redis_session-1.0.1.dist-info/METADATA
naja_atra_redis_session-1.0.1.dist-info/WHEEL
naja_atra_redis_session-1.0.1.dist-info/top_level.txt
naja_atra_redis_session-1.0.1.dist-info/RECORD
