Metadata-Version: 2.1
Name: naja-atra-redis-session
Version: 1.0.1
Summary: This is the redis session implementation for the project [naja atra](https://github.com/naja-atra/naja-atra)
Author-email: keijack <keijack.wu@gmail.com>
License: MIT License
Project-URL: homepage, https://github.com/naja-atra/naja-atra-redis-session
Project-URL: repository, https://github.com/naja-atra/naja-atra-redis-session
Keywords: http-server,websocket,http,web,web-server
Classifier: Programming Language :: Python :: 3
Classifier: License :: OSI Approved :: MIT License
Classifier: Operating System :: OS Independent
Requires-Python: >=3.7
License-File: LICENSE
Requires-Dist: naja-atra
Requires-Dist: redis >=4.3
